{
"meta":{"test_sets":[],"test_metrics":[],"learn_metrics":[{"best_value":"Min","name":"Logloss"}],"launch_mode":"Train","parameters":"","iteration_count":100,"learn_sets":["learn"],"name":"experiment"},
"iterations":[
{"learn":[0.6612020861],"iteration":0,"passed_time":0.056587,"remaining_time":5.602113},
{"learn":[0.6302480373],"iteration":1,"passed_time":0.056916,"remaining_time":2.788884},
{"learn":[0.603771967],"iteration":2,"passed_time":0.0571875,"remaining_time":1.8490625},
{"learn":[0.5837469263],"iteration":3,"passed_time":0.0573855,"remaining_time":1.377252},
{"learn":[0.5671379546],"iteration":4,"passed_time":0.05760454167,"remaining_time":1.094486292},
{"learn":[0.5485201349],"iteration":5,"passed_time":0.05784041667,"remaining_time":0.9061665278},
{"learn":[0.5333490113],"iteration":6,"passed_time":0.058073375,"remaining_time":0.7715462679},
{"learn":[0.5186381479],"iteration":7,"passed_time":0.05828629167,"remaining_time":0.6702923542},
{"learn":[0.5100082169],"iteration":8,"passed_time":0.05850208333,"remaining_time":0.5915210648},
{"learn":[0.4995224846],"iteration":9,"passed_time":0.05873258333,"remaining_time":0.52859325},
{"learn":[0.4923760356],"iteration":10,"passed_time":0.059063375,"remaining_time":0.4778763977},
{"learn":[0.4850777056],"iteration":11,"passed_time":0.059272375,"remaining_time":0.4346640833},
{"learn":[0.4769779988],"iteration":12,"passed_time":0.05950570833,"remaining_time":0.3982305096},
{"learn":[0.4701548263],"iteration":13,"passed_time":0.05970575,"remaining_time":0.3667638929},
{"learn":[0.4638280387],"iteration":14,"passed_time":0.05994841667,"remaining_time":0.3397076944},
{"learn":[0.4578522723],"iteration":15,"passed_time":0.06017779167,"remaining_time":0.3159334062},
{"learn":[0.4529278876],"iteration":16,"passed_time":0.06040975,"remaining_time":0.2949417206},
{"learn":[0.4494326726],"iteration":17,"passed_time":0.06061445833,"remaining_time":0.2761325324},
{"learn":[0.4471026994],"iteration":18,"passed_time":0.060809625,"remaining_time":0.2592410329},
{"learn":[0.4426094918],"iteration":19,"passed_time":0.06102325,"remaining_time":0.244093},
{"learn":[0.4407282328],"iteration":20,"passed_time":0.06120729167,"remaining_time":0.230256002},
{"learn":[0.4378022448],"iteration":21,"passed_time":0.06141116667,"remaining_time":0.2177305},
{"learn":[0.4357130852],"iteration":22,"passed_time":0.0616125,"remaining_time":0.2062679348},
{"learn":[0.4350019622],"iteration":23,"passed_time":0.06181558333,"remaining_time":0.1957493472},
{"learn":[0.4317350775],"iteration":24,"passed_time":0.06199683333,"remaining_time":0.1859905},
{"learn":[0.4288181101],"iteration":25,"passed_time":0.06214525,"remaining_time":0.1768749423},
{"learn":[0.4279014647],"iteration":26,"passed_time":0.06230716667,"remaining_time":0.1684601173},
{"learn":[0.4265216273],"iteration":27,"passed_time":0.06249120833,"remaining_time":0.1606916786},
{"learn":[0.4247025324],"iteration":28,"passed_time":0.06265316667,"remaining_time":0.1533922356},
{"learn":[0.4220590502],"iteration":29,"passed_time":0.062829125,"remaining_time":0.1466012917},
{"learn":[0.4202984233],"iteration":30,"passed_time":0.06299041667,"remaining_time":0.1402044758},
{"learn":[0.4188071764],"iteration":31,"passed_time":0.06327258333,"remaining_time":0.1344542396},
{"learn":[0.417513554],"iteration":32,"passed_time":0.06360754167,"remaining_time":0.1291425846},
{"learn":[0.4163502701],"iteration":33,"passed_time":0.06380766667,"remaining_time":0.1238619412},
{"learn":[0.4156611195],"iteration":34,"passed_time":0.06396795833,"remaining_time":0.1187976369},
{"learn":[0.4146816619],"iteration":35,"passed_time":0.06416133333,"remaining_time":0.1140645926},
{"learn":[0.4137843711],"iteration":36,"passed_time":0.064382625,"remaining_time":0.1096244696},
{"learn":[0.4127534794],"iteration":37,"passed_time":0.06456104167,"remaining_time":0.1053364364},
{"learn":[0.4117771319],"iteration":38,"passed_time":0.06475270833,"remaining_time":0.1012798771},
{"learn":[0.4108351125],"iteration":39,"passed_time":0.06494666667,"remaining_time":0.09742},
{"learn":[0.4102311816],"iteration":40,"passed_time":0.06522316667,"remaining_time":0.09385772764},
{"learn":[0.4098095061],"iteration":41,"passed_time":0.06542025,"remaining_time":0.09034225},
{"learn":[0.4088264381],"iteration":42,"passed_time":0.06559275,"remaining_time":0.08694852907},
{"learn":[0.4073399981],"iteration":43,"passed_time":0.06579829167,"remaining_time":0.0837432803},
{"learn":[0.4067679845],"iteration":44,"passed_time":0.066259,"remaining_time":0.08098322222},
{"learn":[0.4059606736],"iteration":45,"passed_time":0.06650125,"remaining_time":0.07806668478},
{"learn":[0.4053855063],"iteration":46,"passed_time":0.06666379167,"remaining_time":0.07517406294},
{"learn":[0.4044771465],"iteration":47,"passed_time":0.06684579167,"remaining_time":0.07241627431},
{"learn":[0.4039123213],"iteration":48,"passed_time":0.067061375,"remaining_time":0.06979857398},
{"learn":[0.403014624],"iteration":49,"passed_time":0.067262875,"remaining_time":0.067262875},
{"learn":[0.4019933712],"iteration":50,"passed_time":0.06813725,"remaining_time":0.06546520098},
{"learn":[0.4015381006],"iteration":51,"passed_time":0.068332375,"remaining_time":0.06307603846},
{"learn":[0.4011851949],"iteration":52,"passed_time":0.06861625,"remaining_time":0.06084837264},
{"learn":[0.4003161977],"iteration":53,"passed_time":0.06890958333,"remaining_time":0.05870075617},
{"learn":[0.3997445371],"iteration":54,"passed_time":0.06908529167,"remaining_time":0.05652432955},
{"learn":[0.3991669857],"iteration":55,"passed_time":0.069286125,"remaining_time":0.05443909821},
{"learn":[0.3987115527],"iteration":56,"passed_time":0.06948304167,"remaining_time":0.05241703143},
{"learn":[0.398037667],"iteration":57,"passed_time":0.06968683333,"remaining_time":0.05046287931},
{"learn":[0.3978191912],"iteration":58,"passed_time":0.06985725,"remaining_time":0.04854486864},
{"learn":[0.397519591],"iteration":59,"passed_time":0.07006966667,"remaining_time":0.04671311111},
{"learn":[0.3972316751],"iteration":60,"passed_time":0.070256625,"remaining_time":0.04491817008},
{"learn":[0.3964883706],"iteration":61,"passed_time":0.070442125,"remaining_time":0.04317420565},
{"learn":[0.3961970866],"iteration":62,"passed_time":0.07062070833,"remaining_time":0.0414756541},
{"learn":[0.3960018175],"iteration":63,"passed_time":0.07080304167,"remaining_time":0.03982671094},
{"learn":[0.3955997948],"iteration":64,"passed_time":0.070953375,"remaining_time":0.03820566346},
{"learn":[0.3954367618],"iteration":65,"passed_time":0.07113279167,"remaining_time":0.0366441654},
{"learn":[0.394851143],"iteration":66,"passed_time":0.07132520833,"remaining_time":0.03513032649},
{"learn":[0.3946956275],"iteration":67,"passed_time":0.07149125,"remaining_time":0.03364294118},
{"learn":[0.3941159394],"iteration":68,"passed_time":0.07169008333,"remaining_time":0.03220858816},
{"learn":[0.3938354977],"iteration":69,"passed_time":0.0719155,"remaining_time":0.03082092857},
{"learn":[0.3937291773],"iteration":70,"passed_time":0.07211529167,"remaining_time":0.02945554167},
{"learn":[0.3931387868],"iteration":71,"passed_time":0.07233341667,"remaining_time":0.02812966204},
{"learn":[0.3928690769],"iteration":72,"passed_time":0.072517875,"remaining_time":0.02682167979},
{"learn":[0.3928013081],"iteration":73,"passed_time":0.07269875,"remaining_time":0.02554280405},
{"learn":[0.3926855982],"iteration":74,"passed_time":0.07308895833,"remaining_time":0.02436298611},
{"learn":[0.3921630461],"iteration":75,"passed_time":0.07327516667,"remaining_time":0.02313952632},
{"learn":[0.3917487688],"iteration":76,"passed_time":0.07346120833,"remaining_time":0.02194295833},
{"learn":[0.3913600907],"iteration":77,"passed_time":0.07362766667,"remaining_time":0.02076677778},
{"learn":[0.3911255445],"iteration":78,"passed_time":0.0739055,"remaining_time":0.01964576582},
{"learn":[0.3905709829],"iteration":79,"passed_time":0.07404895833,"remaining_time":0.01851223958},
{"learn":[0.3899241736],"iteration":80,"passed_time":0.074224,"remaining_time":0.0174105679},
{"learn":[0.3894082113],"iteration":81,"passed_time":0.07438583333,"remaining_time":0.01632859756},
{"learn":[0.3893160768],"iteration":82,"passed_time":0.074535875,"remaining_time":0.01526638404},
{"learn":[0.3890354767],"iteration":83,"passed_time":0.07470520833,"remaining_time":0.01422956349},
{"learn":[0.3889039472],"iteration":84,"passed_time":0.07482816667,"remaining_time":0.01320497059},
{"learn":[0.388647385],"iteration":85,"passed_time":0.07496445833,"remaining_time":0.01220351647},
{"learn":[0.3883853392],"iteration":86,"passed_time":0.07513929167,"remaining_time":0.01122771025},
{"learn":[0.3882244834],"iteration":87,"passed_time":0.07527566667,"remaining_time":0.01026486364},
{"learn":[0.3881663279],"iteration":88,"passed_time":0.07539645833,"remaining_time":0.00931866339},
{"learn":[0.3881178925],"iteration":89,"passed_time":0.07553133333,"remaining_time":0.00839237037},
{"learn":[0.3880020388],"iteration":90,"passed_time":0.075657,"remaining_time":0.00748256044},
{"learn":[0.3876483153],"iteration":91,"passed_time":0.075797375,"remaining_time":0.006591076087},
{"learn":[0.3874061838],"iteration":92,"passed_time":0.075933,"remaining_time":0.005715387097},
{"learn":[0.3872668774],"iteration":93,"passed_time":0.07606466667,"remaining_time":0.004855191489},
{"learn":[0.3871611121],"iteration":94,"passed_time":0.076214875,"remaining_time":0.004011309211},
{"learn":[0.3867770792],"iteration":95,"passed_time":0.07637008333,"remaining_time":0.003182086806},
{"learn":[0.3866907119],"iteration":96,"passed_time":0.07656054167,"remaining_time":0.002367851804},
{"learn":[0.3861177492],"iteration":97,"passed_time":0.07670458333,"remaining_time":0.00156539966},
{"learn":[0.3859202856],"iteration":98,"passed_time":0.0768755,"remaining_time":0.000776520202},
{"learn":[0.3858805846],"iteration":99,"passed_time":0.07699966667,"remaining_time":0}
]}